kitconcept.timeline-1.0.0a2-py2.7-nspkg.pth
kitconcept/timeline/__init__.py
kitconcept/timeline/configure.zcml
kitconcept/timeline/content.py
kitconcept/timeline/indexers.py
kitconcept/timeline/interfaces.py
kitconcept/timeline/setuphandlers.py
kitconcept/timeline/testing.py
kitconcept/timeline/upgrades.py
kitconcept/timeline/upgrades.zcml
kitconcept/timeline/vocabulary.py
kitconcept/timeline/browser/__init__.py
kitconcept/timeline/browser/configure.zcml
kitconcept/timeline/browser/timeline.pt
kitconcept/timeline/browser/overrides/.gitkeep
kitconcept/timeline/browser/static/.gitkeep
kitconcept/timeline/browser/static/resources.pt
kitconcept/timeline/browser/static/timeline-6cf2d8f.css
kitconcept/timeline/browser/static/timeline-6cf2d8f.js
kitconcept/timeline/locales/collective.timeline.pot
kitconcept/timeline/locales/update.sh
kitconcept/timeline/locales/de/LC_MESSAGES/plone.mo
kitconcept/timeline/locales/de/LC_MESSAGES/plone.po
kitconcept/timeline/profiles/default/browserlayer.xml
kitconcept/timeline/profiles/default/catalog.xml
kitconcept/timeline/profiles/default/cssregistry.xml
kitconcept/timeline/profiles/default/jsregistry.xml
kitconcept/timeline/profiles/default/metadata.xml
kitconcept/timeline/profiles/default/types.xml
kitconcept/timeline/profiles/default/types/Timeline.xml
kitconcept/timeline/profiles/default/types/Timeline_Entry.xml
kitconcept/timeline/profiles/uninstall/browserlayer.xml
kitconcept/timeline/tests/__init__.py
kitconcept/timeline/tests/test_robot.py
kitconcept/timeline/tests/test_setup.py
kitconcept/timeline/tests/test_timeline.py
kitconcept/timeline/tests/test_timeline_entry.py
kitconcept/timeline/tests/robot/test_example.robot
kitconcept.timeline-1.0.0a2.dist-info/METADATA
kitconcept.timeline-1.0.0a2.dist-info/WHEEL
kitconcept.timeline-1.0.0a2.dist-info/entry_points.txt
kitconcept.timeline-1.0.0a2.dist-info/namespace_packages.txt
kitconcept.timeline-1.0.0a2.dist-info/top_level.txt
kitconcept.timeline-1.0.0a2.dist-info/RECORD
